{
    "title": "user_preferences",
    "type": "object",
    "properties": {
        "id": {
            "type": "integer",
            "description": "Primary key, auto-increment"
        },
        "user_id": {
            "type": "string",
            "description": "User ID"
        },
        "theme": {
            "type": "string",
            "description": "Theme preference: light or dark",
            "default": "light"
        },
        "created_at": {
            "type": "string",
            "format": "date-time",
            "description": "Created timestamp"
        },
        "updated_at": {
            "type": "string",
            "format": "date-time",
            "description": "Updated timestamp"
        }
    },
    "required": [
        "id",
        "user_id",
        "theme"
    ]
}